{
  "id": 4,
  "slug": "chon-mau-website-thuong-hieu",
  "title": "Cách chọn bảng màu website theo thương hiệu",
  "excerpt": "Hướng dẫn xây palette ivory – navy – gold: màu chính, màu nhấn và cách giữ contrast để dễ đọc, sang trọng.",
  "thumbnail": "/uploads/thumb-mau-sac.jpg",
  "author": "Admin",
  "authorAvatar": "AD",
  "category": "Thiết kế web",
  "status": "published",
  "publishedAt": "2026-07-09T11:00:00.000Z",
  "scheduledAt": null,
  "views": 72,
  "seo": {
    "metaTitle": "Chọn màu website theo thương hiệu",
    "metaDescription": "Xây bảng màu website sang trọng, dễ đọc và nhất quán thương hiệu.",
    "seoUrl": "/blog/chon-mau-website-thuong-hieu",
    "originalUrl": "/blog/chon-mau-website-thuong-hieu",
    "redirect": null,
    "score": 82,
    "indexStatus": "good"
  },
  "createdAt": "2026-07-07T11:00:00.000Z",
  "updatedAt": "2026-07-09T11:00:00.000Z"
}
